{
	"info": {
		"_postman_id": "1467ee12-efb9-42d6-8a16-ad381c9258fe",
		"name": "Trello REST API",
		"schema": "https://schema.getpostman.com/json/collection/v2.1.0/collection.json"
	},
	"item": [
		{
			"name": "Доска",
			"item": [
				{
					"name": "Создание доски",
					"event": [
						{
							"listen": "test",
							"script": {
								"exec": [
									"pm.test(\"Status code is 200\", function () {\r",
									"    pm.response.to.have.status(200);\r",
									"});\r",
									"pm.test(\"Запись Id доски в переменную\", function () {\r",
									"    var jsonData = pm.response.json();\r",
									"    var value = pm.response.json().id \r",
									"    pm.collectionVariables.set(\"idBoard\", value);\r",
									"});"
								],
								"type": "text/javascript"
							}
						}
					],
					"request": {
						"auth": {
							"type": "noauth"
						},
						"method": "POST",
						"header": [
							{
								"key": "Cookie",
								"value": "token={{myToken}}",
								"type": "text"
							}
						],
						"body": {
							"mode": "raw",
							"raw": "{\r\n    \"defaultLists\": {{$randomBoolean}},\r\n    \"name\": \"{{$randomProductName}}\",\r\n    \"prefs_permissionLevel\": \"private\",\r\n    \"prefs_selfJoin\": false,\r\n    \"idOrganization\": \"6264ba94dfbbde72a3d313e6\",\r\n    \"prefs_background\": \"green\",\r\n    \"token\": \"{{myToken}}\"\r\n}",
							"options": {
								"raw": {
									"language": "json"
								}
							}
						},
						"url": {
							"raw": "{{protocol}}://{{host}}/{{basePath}}boards/",
							"protocol": "{{protocol}}",
							"host": [
								"{{host}}"
							],
							"path": [
								"{{basePath}}boards",
								""
							]
						},
						"description": "Create a new board."
					},
					"response": []
				},
				{
					"name": "Просмотр одной доски",
					"event": [
						{
							"listen": "test",
							"script": {
								"exec": [
									"pm.test(\"Status code is 200\", function () {\r",
									"    pm.response.to.have.status(200);\r",
									"});"
								],
								"type": "text/javascript"
							}
						}
					],
					"protocolProfileBehavior": {
						"disableBodyPruning": true,
						"disabledSystemHeaders": {
							"accept": true
						}
					},
					"request": {
						"auth": {
							"type": "noauth"
						},
						"method": "GET",
						"header": [
							{
								"key": "Accept",
								"value": "application/json"
							},
							{
								"key": "Cookie",
								"value": "token={{myToken}}",
								"type": "text"
							}
						],
						"body": {
							"mode": "raw",
							"raw": "{\r\n    \"token\": \"{{myToken}}\"\r\n}",
							"options": {
								"raw": {
									"language": "json"
								}
							}
						},
						"url": {
							"raw": "{{protocol}}://{{host}}/{{basePath}}boards/{{idBoard}}",
							"protocol": "{{protocol}}",
							"host": [
								"{{host}}"
							],
							"path": [
								"{{basePath}}boards",
								"{{idBoard}}"
							]
						},
						"description": "Request a single board."
					},
					"response": []
				}
			]
		},
		{
			"name": "Списки",
			"item": [
				{
					"name": "Создание нового списка",
					"event": [
						{
							"listen": "test",
							"script": {
								"exec": [
									"pm.test(\"Status code is 200\", function () {\r",
									"    pm.response.to.have.status(200);\r",
									"});\r",
									"pm.test(\"Запись Id списка в переменную\", function () {\r",
									"    var jsonData = pm.response.json();\r",
									"    var value = pm.response.json().id \r",
									"    pm.collectionVariables.set(\"idList\", value);\r",
									"});"
								],
								"type": "text/javascript"
							}
						}
					],
					"request": {
						"auth": {
							"type": "noauth"
						},
						"method": "POST",
						"header": [
							{
								"key": "Cookie",
								"value": "token={{myToken}}",
								"type": "text"
							}
						],
						"body": {
							"mode": "raw",
							"raw": "{\r\n    \"name\": \"{{$randomLoremWord}}\",\r\n    \"pos\": \"top\",\r\n    \"closed\": false,\r\n    \"idBoard\": \"{{idBoard}}\",\r\n    \"token\": \"{{myToken}}\"\r\n}",
							"options": {
								"raw": {
									"language": "json"
								}
							}
						},
						"url": {
							"raw": "{{protocol}}://{{host}}/{{basePath}}lists/",
							"protocol": "{{protocol}}",
							"host": [
								"{{host}}"
							],
							"path": [
								"{{basePath}}lists",
								""
							]
						},
						"description": "Create a new List on a Board"
					},
					"response": []
				},
				{
					"name": "Создание второго списка",
					"event": [
						{
							"listen": "test",
							"script": {
								"exec": [
									"pm.test(\"Status code is 200\", function () {\r",
									"    pm.response.to.have.status(200);\r",
									"});\r",
									"pm.test(\"Запись Id списка в переменную\", function () {\r",
									"    var jsonData = pm.response.json();\r",
									"    var value = pm.response.json().id \r",
									"    pm.collectionVariables.set(\"idList2\", value);\r",
									"});"
								],
								"type": "text/javascript"
							}
						}
					],
					"request": {
						"auth": {
							"type": "noauth"
						},
						"method": "POST",
						"header": [
							{
								"key": "Cookie",
								"value": "token={{myToken}}",
								"type": "text"
							}
						],
						"body": {
							"mode": "raw",
							"raw": "{\r\n    \"name\": \"{{$randomLoremWord}}\",\r\n    \"pos\": \"top\",\r\n    \"closed\": false,\r\n    \"idBoard\": \"{{idBoard}}\",\r\n    \"token\": \"{{myToken}}\"\r\n}",
							"options": {
								"raw": {
									"language": "json"
								}
							}
						},
						"url": {
							"raw": "{{protocol}}://{{host}}/{{basePath}}lists/",
							"protocol": "{{protocol}}",
							"host": [
								"{{host}}"
							],
							"path": [
								"{{basePath}}lists",
								""
							]
						},
						"description": "Create a new List on a Board"
					},
					"response": []
				},
				{
					"name": "Просмотр созданного списка",
					"event": [
						{
							"listen": "test",
							"script": {
								"exec": [
									"pm.test(\"Status code is 200\", function () {\r",
									"    pm.response.to.have.status(200);\r",
									"});"
								],
								"type": "text/javascript"
							}
						}
					],
					"protocolProfileBehavior": {
						"disableBodyPruning": true
					},
					"request": {
						"auth": {
							"type": "noauth"
						},
						"method": "GET",
						"header": [
							{
								"key": "Cookie",
								"value": "token={{myToken}}",
								"type": "text"
							}
						],
						"body": {
							"mode": "raw",
							"raw": "{\r\n    \"token\": \"{{myToken}}\"\r\n}",
							"options": {
								"raw": {
									"language": "json"
								}
							}
						},
						"url": {
							"raw": "{{protocol}}://{{host}}/{{basePath}}lists/{{idList}}",
							"protocol": "{{protocol}}",
							"host": [
								"{{host}}"
							],
							"path": [
								"{{basePath}}lists",
								"{{idList}}"
							]
						},
						"description": "Get information about a List"
					},
					"response": []
				}
			]
		},
		{
			"name": "Карточки",
			"item": [
				{
					"name": "Создание карточки",
					"event": [
						{
							"listen": "test",
							"script": {
								"exec": [
									"pm.test(\"Status code is 200\", function () {\r",
									"    pm.response.to.have.status(200);\r",
									"});\r",
									"pm.test(\"Запись Id задачи в переменную\", function () {\r",
									"    var jsonData = pm.response.json();\r",
									"    var value = pm.response.json().id \r",
									"    pm.collectionVariables.set(\"idCard\", value);\r",
									"});"
								],
								"type": "text/javascript"
							}
						}
					],
					"request": {
						"auth": {
							"type": "noauth"
						},
						"method": "POST",
						"header": [
							{
								"key": "Accept",
								"value": "application/json"
							},
							{
								"key": "Cookie",
								"value": "token={{myToken}}",
								"type": "text"
							}
						],
						"body": {
							"mode": "raw",
							"raw": "{\r\n    \"name\": \"{{$randomLoremSentence}}\",\r\n    \"closed\": false,\r\n    \"idLabels\": [],\r\n    \"idMembers\": [],\r\n    \"dateLastActivity\": 1650782175943,\r\n    \"pos\": \"bottom\",\r\n    \"cardRole\": null,\r\n    \"idBoard\": \"{{idBoard}}\",\r\n    \"idList\": \"{{idList}}\",\r\n    \"token\": \"{{myToken}}\"\r\n}",
							"options": {
								"raw": {
									"language": "json"
								}
							}
						},
						"url": {
							"raw": "{{protocol}}://{{host}}/{{basePath}}cards/",
							"protocol": "{{protocol}}",
							"host": [
								"{{host}}"
							],
							"path": [
								"{{basePath}}cards",
								""
							]
						},
						"description": "Create a new card"
					},
					"response": []
				},
				{
					"name": "Изменение названия карточки",
					"event": [
						{
							"listen": "test",
							"script": {
								"exec": [
									"pm.test(\"Status code is 200\", function () {\r",
									"    pm.response.to.have.status(200);\r",
									"});"
								],
								"type": "text/javascript"
							}
						}
					],
					"request": {
						"auth": {
							"type": "noauth"
						},
						"method": "PUT",
						"header": [
							{
								"key": "Accept",
								"value": "application/json"
							},
							{
								"key": "Cookie",
								"value": "token={{myToken}}",
								"type": "text"
							}
						],
						"body": {
							"mode": "raw",
							"raw": "{\r\n    \"token\": \"{{myToken}}\",\r\n    \"name\": \"{{$randomLoremSentence}}\",\r\n    \"idBoard\": \"{{idBoard}}\",\r\n    \"idList\": \"{{idList}}\"\r\n}",
							"options": {
								"raw": {
									"language": "json"
								}
							}
						},
						"url": {
							"raw": "{{protocol}}://{{host}}/{{basePath}}cards/{{idCard}}",
							"protocol": "{{protocol}}",
							"host": [
								"{{host}}"
							],
							"path": [
								"{{basePath}}cards",
								"{{idCard}}"
							]
						},
						"description": "Update a card"
					},
					"response": []
				},
				{
					"name": "Добавление комментария к карточке",
					"event": [
						{
							"listen": "test",
							"script": {
								"exec": [
									"pm.test(\"Status code is 200\", function () {\r",
									"    pm.response.to.have.status(200);\r",
									"});"
								],
								"type": "text/javascript"
							}
						}
					],
					"request": {
						"auth": {
							"type": "noauth"
						},
						"method": "POST",
						"header": [
							{
								"key": "Accept",
								"value": "application/json"
							},
							{
								"key": "Cookie",
								"value": "token={{myToken}}",
								"type": "text"
							}
						],
						"body": {
							"mode": "raw",
							"raw": "{\r\n    \"token\": \"{{myToken}}\",\r\n    \"text\": \"{{$randomLoremParagraph}}\"\r\n}",
							"options": {
								"raw": {
									"language": "json"
								}
							}
						},
						"url": {
							"raw": "{{protocol}}://{{host}}/{{basePath}}cards/{{idCard}}/actions/comments/",
							"protocol": "{{protocol}}",
							"host": [
								"{{host}}"
							],
							"path": [
								"{{basePath}}cards",
								"{{idCard}}",
								"actions",
								"comments",
								""
							]
						},
						"description": "Add a new comment to a card"
					},
					"response": []
				},
				{
					"name": "Перемещение карточки во второй список",
					"event": [
						{
							"listen": "test",
							"script": {
								"exec": [
									"pm.test(\"Status code is 200\", function () {\r",
									"    pm.response.to.have.status(200);\r",
									"});"
								],
								"type": "text/javascript"
							}
						}
					],
					"request": {
						"auth": {
							"type": "noauth"
						},
						"method": "PUT",
						"header": [
							{
								"key": "Accept",
								"value": "application/json"
							},
							{
								"key": "Cookie",
								"value": "token={{myToken}}",
								"type": "text"
							}
						],
						"body": {
							"mode": "raw",
							"raw": "{\r\n    \"token\": \"{{myToken}}\",\r\n    \"idBoard\": \"{{idBoard}}\",\r\n    \"idList\": \"{{idList2}}\"\r\n}",
							"options": {
								"raw": {
									"language": "json"
								}
							}
						},
						"url": {
							"raw": "{{protocol}}://{{host}}/{{basePath}}cards/{{idCard}}",
							"protocol": "{{protocol}}",
							"host": [
								"{{host}}"
							],
							"path": [
								"{{basePath}}cards",
								"{{idCard}}"
							]
						},
						"description": "Update a card"
					},
					"response": []
				},
				{
					"name": "Просмотр карточки",
					"event": [
						{
							"listen": "test",
							"script": {
								"exec": [
									"pm.test(\"Status code is 200\", function () {\r",
									"    pm.response.to.have.status(200);\r",
									"});"
								],
								"type": "text/javascript"
							}
						}
					],
					"protocolProfileBehavior": {
						"disableBodyPruning": true
					},
					"request": {
						"auth": {
							"type": "noauth"
						},
						"method": "GET",
						"header": [
							{
								"key": "Accept",
								"value": "application/json"
							},
							{
								"key": "Cookie",
								"value": "token={{myToken}}",
								"type": "text"
							}
						],
						"body": {
							"mode": "raw",
							"raw": "{\r\n    \"token\": \"{{myToken}}\"\r\n}",
							"options": {
								"raw": {
									"language": "json"
								}
							}
						},
						"url": {
							"raw": "{{protocol}}://{{host}}/{{basePath}}cards/{{idCard}}",
							"protocol": "{{protocol}}",
							"host": [
								"{{host}}"
							],
							"path": [
								"{{basePath}}cards",
								"{{idCard}}"
							]
						},
						"description": "Get a card by its ID"
					},
					"response": []
				},
				{
					"name": "Удаление карточки",
					"event": [
						{
							"listen": "test",
							"script": {
								"exec": [
									"pm.test(\"Status code is 200\", function () {\r",
									"    pm.response.to.have.status(200);\r",
									"});"
								],
								"type": "text/javascript"
							}
						}
					],
					"request": {
						"auth": {
							"type": "noauth"
						},
						"method": "DELETE",
						"header": [
							{
								"key": "Cookie",
								"value": "token={{myToken}}",
								"type": "text"
							}
						],
						"body": {
							"mode": "raw",
							"raw": "{\r\n    \"token\": \"{{myToken}}\"\r\n}",
							"options": {
								"raw": {
									"language": "json"
								}
							}
						},
						"url": {
							"raw": "{{protocol}}://{{host}}/{{basePath}}cards/{{idCard}}",
							"protocol": "{{protocol}}",
							"host": [
								"{{host}}"
							],
							"path": [
								"{{basePath}}cards",
								"{{idCard}}"
							]
						},
						"description": "Delete a Card"
					},
					"response": []
				}
			]
		},
		{
			"name": "Удаление доски",
			"event": [
				{
					"listen": "test",
					"script": {
						"exec": [
							"pm.test(\"Status code is 200\", function () {\r",
							"    pm.response.to.have.status(200);\r",
							"});"
						],
						"type": "text/javascript"
					}
				}
			],
			"request": {
				"auth": {
					"type": "noauth"
				},
				"method": "DELETE",
				"header": [
					{
						"key": "Cookie",
						"value": "token={{myToken}}",
						"type": "text"
					}
				],
				"body": {
					"mode": "raw",
					"raw": "{\r\n    \"token\": \"{{myToken}}\"\r\n}",
					"options": {
						"raw": {
							"language": "json"
						}
					}
				},
				"url": {
					"raw": "{{protocol}}://{{host}}/{{basePath}}boards/{{idBoard}}",
					"protocol": "{{protocol}}",
					"host": [
						"{{host}}"
					],
					"path": [
						"{{basePath}}boards",
						"{{idBoard}}"
					]
				},
				"description": "Delete a board."
			},
			"response": []
		}
	],
	"event": [
		{
			"listen": "prerequest",
			"script": {
				"type": "text/javascript",
				"exec": [
					""
				]
			}
		},
		{
			"listen": "test",
			"script": {
				"type": "text/javascript",
				"exec": [
					""
				]
			}
		}
	],
	"variable": [
		{
			"key": "protocol",
			"value": "https",
			"type": "string"
		},
		{
			"key": "host",
			"value": "api.trello.com",
			"type": "string"
		},
		{
			"key": "basePath",
			"value": "1/",
			"type": "string"
		},
		{
			"key": "myToken",
			"value": "6264ba70be954d31d355ac80/uccnHFttrSfJDn8JCLeRx78SGMMNkkihilWbJF2D7u11l4fNHKuNWz4WeIfUMeRb",
			"type": "string"
		},
		{
			"key": "idBoard",
			"value": "6264e6799dd11b0fb4bb27f3",
			"type": "string"
		},
		{
			"key": "idList",
			"value": ""
		},
		{
			"key": "idCard",
			"value": ""
		},
		{
			"key": "idList2",
			"value": ""
		}
	]
}